ai_cache/__init__.py
ai_cache/cache_engine.py
ai_cache/core.py
ai_cache/interceptors/__init__.py
ai_cache/interceptors/anthropic.py
ai_cache/interceptors/gemini.py
ai_cache/interceptors/openai.py
ai_cache-0.1.1.dist-info/licenses/LICENSE
ai_cache-0.1.1.dist-info/METADATA
ai_cache-0.1.1.dist-info/WHEEL
ai_cache-0.1.1.dist-info/top_level.txt
ai_cache-0.1.1.dist-info/RECORD
