Metadata-Version: 2.4
Name: ai-cache
Version: 0.1.1
Summary: Lightweight automatic caching for LLM API responses
Author-email: Abdur Rafay <abdurrafay432007@gmail.com>
License: MIT
Project-URL: Homepage, https://github.com/Abdur-Rafay-AR/ai-cache
Project-URL: Repository, https://github.com/Abdur-Rafay-AR/ai-cache
Project-URL: Issues, https://github.com/Abdur-Rafay-AR/ai-cache/issues
Keywords: llm,cache,openai,anthropic,gemini,ai,api
Classifier: Development Status :: 4 - Beta
Classifier: Intended Audience :: Developers
Classifier: License :: OSI Approved :: MIT License
Classifier: Programming Language :: Python :: 3
Classifier: Programming Language :: Python :: 3.8
Classifier: Programming Language :: Python :: 3.9
Classifier: Programming Language :: Python :: 3.10
Classifier: Programming Language :: Python :: 3.11
Classifier: Programming Language :: Python :: 3.12
Classifier: Topic :: Software Development :: Libraries :: Python Modules
Classifier: Topic :: Scientific/Engineering :: Artificial Intelligence
Requires-Python: >=3.8
License-File: LICENSE
Provides-Extra: dev
Requires-Dist: pytest>=7.0; extra == "dev"
Requires-Dist: pytest-cov>=4.0; extra == "dev"
Requires-Dist: black>=23.0; extra == "dev"
Requires-Dist: ruff>=0.1.0; extra == "dev"
Dynamic: license-file
